syft_notebook_ui/__init__.py
syft_notebook_ui/display.py
syft_notebook_ui/formatter_mixin.py
syft_notebook_ui/icons.py
syft_notebook_ui/pydantic_html_repr.py
syft_notebook_ui/resources.py
syft_notebook_ui/sanitize.py
syft_notebook_ui/table_utils.py
syft_notebook_ui/tabulator.py
syft_notebook_ui/types.py
syft_notebook_ui/utils.py
syft_notebook_ui/assets/adjectives.txt
syft_notebook_ui/assets/data_access_template.py.jinja
syft_notebook_ui/assets/nouns.txt
syft_notebook_ui/assets/css/fonts.css
syft_notebook_ui/assets/css/model_repr.css
syft_notebook_ui/assets/css/style.css
syft_notebook_ui/assets/css/tabulator_pysyft.min.css
syft_notebook_ui/assets/jinja/model_repr.jinja2
syft_notebook_ui/assets/jinja/model_repr_file_section.jinja2
syft_notebook_ui/assets/jinja/syft_exception.jinja2
syft_notebook_ui/assets/jinja/table.jinja2
syft_notebook_ui/assets/js/table.js
syft_notebook_ui/assets/js/tabulator.min.js
syft_notebook_ui/assets/svg/arrow.svg
syft_notebook_ui/assets/svg/clipboard.svg
syft_notebook_ui/assets/svg/copy.svg
syft_notebook_ui/assets/svg/folder.svg
syft_notebook_ui/assets/svg/info.svg
syft_notebook_ui/assets/svg/request.svg
syft_notebook_ui/assets/svg/search.svg
syft_notebook_ui/assets/svg/table.svg
syft_notebook_ui-0.1.0.dist-info/METADATA
syft_notebook_ui-0.1.0.dist-info/WHEEL
syft_notebook_ui-0.1.0.dist-info/RECORD
