Metadata-Version: 2.4
Name: syft-notebook-ui
Version: 0.1.0
Summary: Add your description here
Author: openmined
Requires-Python: >=3.9
Requires-Dist: ipython>=8.18.1
Requires-Dist: jinja2>=3.1.6
Requires-Dist: loguru>=0.7.3
Requires-Dist: nh3>=0.2.21
Requires-Dist: pydantic[email]>=2.10.4
Requires-Dist: rich>=13.9.4
